pysdd/__init__.py
pysdd/__main__.py
pysdd/cli.py
pysdd/iterator.py
pysdd/sdd.cpython-313-x86_64-linux-gnu.so
pysdd/sdd.pyx
pysdd/util.py
pysdd/wmcstochastic.py
pysdd/lib/libsdd-2.0/src/util.c
pysdd/lib/libsdd-2.0/src/verify.c
pysdd/lib/libsdd-2.0/src/version.c
pysdd/lib/libsdd-2.0/src/basic/computed.c
pysdd/lib/libsdd-2.0/src/basic/count_and_size.c
pysdd/lib/libsdd-2.0/src/basic/gc.c
pysdd/lib/libsdd-2.0/src/basic/hash.c
pysdd/lib/libsdd-2.0/src/basic/memory.c
pysdd/lib/libsdd-2.0/src/basic/multiply.c
pysdd/lib/libsdd-2.0/src/basic/nodes.c
pysdd/lib/libsdd-2.0/src/basic/partitions.c
pysdd/lib/libsdd-2.0/src/basic/references.c
pysdd/lib/libsdd-2.0/src/basic/replace.c
pysdd/lib/libsdd-2.0/src/basic/shadows.c
pysdd/lib/libsdd-2.0/src/basic/sort.c
pysdd/lib/libsdd-2.0/src/manager/copy.c
pysdd/lib/libsdd-2.0/src/manager/interface.c
pysdd/lib/libsdd-2.0/src/manager/manager.c
pysdd/lib/libsdd-2.0/src/manager/stats.c
pysdd/lib/libsdd-2.0/src/manager/variables.c
pysdd/lib/libsdd-2.0/src/sdds/apply.c
pysdd/lib/libsdd-2.0/src/sdds/bits.c
pysdd/lib/libsdd-2.0/src/sdds/cardinality.c
pysdd/lib/libsdd-2.0/src/sdds/condition.c
pysdd/lib/libsdd-2.0/src/sdds/copy.c
pysdd/lib/libsdd-2.0/src/sdds/count.c
pysdd/lib/libsdd-2.0/src/sdds/essential_vars.c
pysdd/lib/libsdd-2.0/src/sdds/exists.c
pysdd/lib/libsdd-2.0/src/sdds/exists_multiple.c
pysdd/lib/libsdd-2.0/src/sdds/exists_multiple_static.c
pysdd/lib/libsdd-2.0/src/sdds/forall.c
pysdd/lib/libsdd-2.0/src/sdds/io.c
pysdd/lib/libsdd-2.0/src/sdds/model_count.c
pysdd/lib/libsdd-2.0/src/sdds/rename_vars.c
pysdd/lib/libsdd-2.0/src/sdds/size.c
pysdd/lib/libsdd-2.0/src/sdds/wmc.c
pysdd/lib/libsdd-2.0/src/vtree_fragments/construction.c
pysdd/lib/libsdd-2.0/src/vtree_fragments/moves.c
pysdd/lib/libsdd-2.0/src/vtree_fragments/operations.c
pysdd/lib/libsdd-2.0/src/vtree_operations/cartesian_product.c
pysdd/lib/libsdd-2.0/src/vtree_operations/dissect.c
pysdd-1.0.6.dist-info/METADATA
pysdd-1.0.6.dist-info/WHEEL
pysdd-1.0.6.dist-info/entry_points.txt
pysdd-1.0.6.dist-info/top_level.txt
pysdd-1.0.6.dist-info/RECORD
pysdd-1.0.6.dist-info/licenses/LICENSE
