Metadata-Version: 2.1
Name: PySDD
Version: 1.0.6
Summary: Sentential Decision Diagrams
Author: Arthur Choi
Author-email: Wannes Meert <wannes.meert@cs.kuleuven.be>, Robin Manhaeve <robin.manhaeve@kuleuven.be>
License: Copyright 2018, KU Leuven and Regents of the University of California
Project-URL: Homepage, https://github.com/wannesm/PySDD
Project-URL: Documentation, https://pysdd.readthedocs.io/en/latest/
Keywords: sdd, knowledge compilation
Classifier: Intended Audience :: Developers
Classifier: License :: OSI Approved :: Apache Software License
Classifier: Programming Language :: Python :: 3
Classifier: Topic :: Scientific/Engineering :: Artificial Intelligence
Requires-Python: >=3.8
License-File: LICENSE
Requires-Dist: cython
Provides-Extra: notebooks
Requires-Dist: numpy ; extra == 'notebooks'
Provides-Extra: tests
Requires-Dist: pytest ; extra == 'tests'
